README.md
setup.cfg
setup.py
ie_mbdbl2018_riyadk/__init__.py
ie_mbdbl2018_riyadk.egg-info/PKG-INFO
ie_mbdbl2018_riyadk.egg-info/SOURCES.txt
ie_mbdbl2018_riyadk.egg-info/dependency_links.txt
ie_mbdbl2018_riyadk.egg-info/not-zip-safe
ie_mbdbl2018_riyadk.egg-info/top_level.txt