Metadata-Version: 1.0
Name: ie-mbdbl2018-riyadk
Version: 0.1
Summary: Python Packaging Starting Kit - Simple Structure to creater your own package - for training purposes!
Home-page: https://github.com/Riyadkutabish
Author: Riyad Kutabish
Author-email: riyad.kutabish@student.ie.edu
License: MIT
Platform: UNKNOWN
